PourPy/__init__.py
PourPy/common.py
PourPy/database.py
PourPy/parser.py
PourPy/pourbaix.py
PourPy/reactant.py
PourPy/reaction.py
PourPy/system.py
PourPy-1.1.1.dist-info/LICENSE
PourPy-1.1.1.dist-info/METADATA
PourPy-1.1.1.dist-info/WHEEL
PourPy-1.1.1.dist-info/top_level.txt
PourPy-1.1.1.dist-info/RECORD
