Metadata-Version: 2.1
Name: PourPy
Version: 1.1.1
Summary: A Python-based library to generate Pourbaix diagrams (potential/pH diagram)
Home-page: https://gitlab.com/cmbm-ethz/pourbaix-diagrams
Author: Fabio Furcas, Anja Korber, Mohit Pundir
Author-email: Mohit Pundir <mpundir@ethz.ch>, "Fabio E. Furcas" <ffurcas@ethz.ch>
License: GNU GENERAL PUBLIC LICENSE
Project-URL: Homepage, https://gitlab.com/cmbm-ethz/pourbaix-diagrams
Project-URL: Issues, https://gitlab.com/cmbm-ethz/pourbaix-diagrams/issues
Keywords: potential-diagram,pourbaix,chemical
Classifier: Programming Language :: Python :: 3
Classifier: License :: OSI Approved :: MIT License
Requires-Python: >=3.8
License-File: LICENSE
Requires-Dist: argparse
Requires-Dist: bokeh
Requires-Dist: matplotlib
Requires-Dist: shapely
Requires-Dist: nbsphinx
Requires-Dist: sphinx-autoapi
Requires-Dist: sphinx-rtd-theme
Requires-Dist: tomli ; python_version < "3.11"
Provides-Extra: test
Requires-Dist: pytest ; extra == 'test'
